paur/__init__.py
paur/paur.py
paur/init/__init__.py
paur/init/utils.py
paur/utils/__init__.py
paur/utils/conf.py
paur-0.0.1a0.dist-info/LICENSE
paur-0.0.1a0.dist-info/METADATA
paur-0.0.1a0.dist-info/WHEEL
paur-0.0.1a0.dist-info/top_level.txt
paur-0.0.1a0.dist-info/RECORD
