Metadata-Version: 2.1
Name: paur
Version: 0.0.1a0
Summary: A python wrapper pacman with the ability to interact with Arch User Repository
Home-page: https://github.com/tonybenoy/paur
Author: Tony Benoy
Author-email: me@tonybenoy.com
License: UNKNOWN
Keywords: Arch Linux AUR Arch User Repository pacman
Platform: UNKNOWN
Classifier: Programming Language :: Python :: 3
Classifier: License :: OSI Approved :: BSD License
Classifier: Operating System :: POSIX :: Linux
Classifier: Development Status :: 2 - Pre-Alpha
Requires-Python: >=3.7
Requires-Dist: typer
Requires-Dist: shellingham
Requires-Dist: aurlib
Requires-Dist: aorlib
Requires-Dist: aiosqlite
Provides-Extra: dev
Requires-Dist: black ; extra == 'dev'
Requires-Dist: pylint ; extra == 'dev'
Requires-Dist: isort ; extra == 'dev'
Requires-Dist: mypy ; extra == 'dev'
